{
  "db_name": "PostgreSQL",
  "query": "\n        SELECT\n          audit_logs.actor_id as \"audit_actor_id\",\n          audit_logs.is_sudo as \"audit_is_sudo\",\n          audit_logs.action as \"audit_action\",\n          audit_logs.meta as \"audit_meta\",\n          audit_logs.created_at\n        FROM\n          audit_logs\n        WHERE \n          audit_logs.meta::text LIKE $1;\n        ",
  "describe": {
    "columns": [
      {
        "ordinal": 0,
        "name": "audit_actor_id",
        "type_info": "Uuid"
      },
      {
        "ordinal": 1,
        "name": "audit_is_sudo",
        "type_info": "Bool"
      },
      {
        "ordinal": 2,
        "name": "audit_action",
        "type_info": "Text"
      },
      {
        "ordinal": 3,
        "name": "audit_meta",
        "type_info": "Jsonb"
      },
      {
        "ordinal": 4,
        "name": "created_at",
        "type_info": "Timestamptz"
      }
    ],
    "parameters": {
      "Left": [
        "Text"
      ]
    },
    "nullable": [
      false,
      false,
      false,
      false,
      false
    ]
  },
  "hash": "2ab4e62ffc27c4ead74a73ff378cad6802fe46500692fa26cb2cc3d693e76ece"
}
